generator/__init__.py
generator/__main__.py
generator/decorators.py
generator/functions.py
generator/help.md
generator/file_manager/__init__.py
generator/file_manager/manager.py
generator/file_templates/config.template
generator/file_templates/component/html.txt
generator/file_templates/component/index.txt
generator/file_templates/component/js.txt
generator/file_templates/component/scss.txt
generator/file_templates/component/vue.txt
generator/file_templates/filter/js.txt
generator/file_templates/filter/register.txt
generator/file_templates/route/route.txt
generator/utils/__init__.py
generator/utils/constants.cfg
generator/utils/utils.py
py_generator-0.2.1.dist-info/DESCRIPTION.rst
py_generator-0.2.1.dist-info/METADATA
py_generator-0.2.1.dist-info/RECORD
py_generator-0.2.1.dist-info/WHEEL
py_generator-0.2.1.dist-info/entry_points.txt
py_generator-0.2.1.dist-info/metadata.json
py_generator-0.2.1.dist-info/top_level.txt
