Metadata-Version: 2.0
Name: py-generator
Version: 0.2.1
Summary: File generator and developer's helper written in python
Home-page: http://github.com/jdimodugno/py-generator
Author: Juan Di Modugno
Author-email: dimodugnojuan@gmail.com
License: UNKNOWN
Platform: UNKNOWN
